crfseg/__init__.py
crfseg/meanfield.py
crfseg/utils.py
crfseg-0.1.3.dist-info/LICENSE
crfseg-0.1.3.dist-info/METADATA
crfseg-0.1.3.dist-info/WHEEL
crfseg-0.1.3.dist-info/top_level.txt
crfseg-0.1.3.dist-info/RECORD
