Metadata-Version: 2.1
Name: crfseg
Version: 0.1.3
Summary: PyTorch implementation of conditional random field for multiclass semantic segmenation.
Home-page: http://github.com/migonch/crfseg
Author: Mikhail Goncharov, Stanislav Shimovolos
Author-email: goncharov.myu@phystech.edu
License: MIT
Platform: UNKNOWN
Requires-Python: >=3.6
Requires-Dist: numpy
Requires-Dist: torch
Requires-Dist: torchvision
